README.rst
setup.cfg
setup.py
python_xbrl_middleware.egg-info/PKG-INFO
python_xbrl_middleware.egg-info/SOURCES.txt
python_xbrl_middleware.egg-info/dependency_links.txt
python_xbrl_middleware.egg-info/requires.txt
python_xbrl_middleware.egg-info/top_level.txt
xbrl_middleware/__init__.py
xbrl_middleware/dump_excel.py