Metadata-Version: 1.1
Name: python-xbrl-middleware
Version: 0.0.1
Summary: various python-xbrl middlewares
Home-page: https://github.com/greedo/python-xbrl-middleware/
Author: Joe Cabrera
Author-email: jcabrera@eminorlabs.com
License: Apache License
Keywords: xbrl,Financial,Accounting,file formats
Platform: UNKNOWN
Classifier: Intended Audience :: Developers
Classifier: Natural Language :: English
Classifier: Operating System :: OS Independent
Classifier: Programming Language :: Python :: 2
Classifier: Programming Language :: Python :: 2.6
Classifier: Programming Language :: Python :: 2.7
Classifier: Programming Language :: Python :: 3
Classifier: Programming Language :: Python :: 3.3
Classifier: Programming Language :: Python :: 3.4
Classifier: Topic :: Software Development :: Libraries :: Python Modules
Classifier: Topic :: Office/Business :: Financial
